tfrec_literate/__init__.py
tfrec_literate/read.py
tfrec_literate/write.py
tfrec_literate-2.10.0rc1.dist-info/licenses/LICENSE
tfrec_literate-2.10.0rc1.dist-info/METADATA
tfrec_literate-2.10.0rc1.dist-info/WHEEL
tfrec_literate-2.10.0rc1.dist-info/top_level.txt
tfrec_literate-2.10.0rc1.dist-info/RECORD
